document_parse/__init__.py
document_parse/llamaparse.py
document_parse/main_file_s3_to_llamaparse.py
mcp_survey/__init__.py
mcp_survey/__main__.py
mcp_survey/constants.py
mcp_survey/credentials.py
mcp_survey/databases.py
mcp_survey/generate_mail_html.py
mcp_survey/html_link_from_md.py
mcp_survey/prompts.py
mcp_survey/resources.py
mcp_survey/server.py
mcp_survey/tool_schema.py
mcp_survey/tools.py
mcp_survey/utils.py
mcp_survey/Agent/main.py
mcp_survey/Agent/markdown_logger.py
mcp_survey/Agent/setup.py
mcp_survey/Agent/app/__init__.py
mcp_survey/Agent/app/bedrock.py
mcp_survey/Agent/app/config.py
mcp_survey/Agent/app/exceptions.py
mcp_survey/Agent/app/llm.py
mcp_survey/Agent/app/logger.py
mcp_survey/Agent/app/schema.py
mcp_survey/Agent/app/toolHandler.py
mcp_survey/Agent/app/agent/__init__.py
mcp_survey/Agent/app/agent/base.py
mcp_survey/Agent/app/agent/casefileAgent.py
mcp_survey/Agent/app/agent/react.py
mcp_survey/Agent/app/agent/toolcall.py
mcp_survey/Agent/app/sandbox/__init__.py
mcp_survey/Agent/app/sandbox/client.py
mcp_survey/Agent/app/sandbox/core/exceptions.py
mcp_survey/Agent/app/sandbox/core/manager.py
mcp_survey/Agent/app/sandbox/core/sandbox.py
mcp_survey/Agent/app/sandbox/core/terminal.py
mcp_survey/Agent/app/tool/__init__.py
mcp_survey/Agent/app/tool/base.py
mcp_survey/Agent/app/tool/create_chat_completion.py
mcp_survey/Agent/app/tool/mcp_tool.py
mcp_survey/Agent/app/tool/terminate.py
mcp_survey/Agent/app/tool/tool_collection.py
mcp_survey/Agent/app/tool/search/__init__.py
mcp_survey/Agent/app/tool/search/baidu_search.py
mcp_survey/Agent/app/tool/search/base.py
mcp_survey/Agent/app/tool/search/bing_search.py
mcp_survey/Agent/app/tool/search/duckduckgo_search.py
mcp_survey/Agent/app/tool/search/google_search.py
mcp_survey/Agent/app/tool/search/vessel_database_search.py
mcp_survey/Agent/app/tool/search/vessel_search.py
mcp_survey/Agent/config/config.toml
mcp_survey/Agent/config/mcp_servers_config.json
mcp_survey/Agent/config/tools.json
syia_mcp_survey_2025_x7k9-0.1.17.dist-info/METADATA
syia_mcp_survey_2025_x7k9-0.1.17.dist-info/WHEEL
syia_mcp_survey_2025_x7k9-0.1.17.dist-info/top_level.txt
syia_mcp_survey_2025_x7k9-0.1.17.dist-info/RECORD
